.DS_Store
CNOunlimited/__init__.py
CNOunlimited/sql_conn.py
CNOunlimited/token_grabber.py
CNOunlimited-0.1.7.dist-info/LICENSE
CNOunlimited-0.1.7.dist-info/METADATA
CNOunlimited-0.1.7.dist-info/WHEEL
CNOunlimited-0.1.7.dist-info/top_level.txt
CNOunlimited-0.1.7.dist-info/RECORD
